odoo/addons/currency_rate_update_transferwise/README.rst
odoo/addons/currency_rate_update_transferwise/__init__.py
odoo/addons/currency_rate_update_transferwise/__manifest__.py
odoo/addons/currency_rate_update_transferwise/i18n/currency_rate_update_transferwise.pot
odoo/addons/currency_rate_update_transferwise/i18n/es.po
odoo/addons/currency_rate_update_transferwise/i18n/fr.po
odoo/addons/currency_rate_update_transferwise/i18n/it.po
odoo/addons/currency_rate_update_transferwise/models/__init__.py
odoo/addons/currency_rate_update_transferwise/models/res_company.py
odoo/addons/currency_rate_update_transferwise/models/res_config_settings.py
odoo/addons/currency_rate_update_transferwise/models/res_currency_rate_provider_TransferWise.py
odoo/addons/currency_rate_update_transferwise/readme/CONFIGURE.rst
odoo/addons/currency_rate_update_transferwise/readme/CONTRIBUTORS.rst
odoo/addons/currency_rate_update_transferwise/readme/DESCRIPTION.rst
odoo/addons/currency_rate_update_transferwise/static/description/icon.png
odoo/addons/currency_rate_update_transferwise/static/description/index.html
odoo/addons/currency_rate_update_transferwise/tests/__init__.py
odoo/addons/currency_rate_update_transferwise/tests/test_currency_rate_update_transferwise.py
odoo/addons/currency_rate_update_transferwise/views/res_config_settings.xml
odoo14_addon_currency_rate_update_transferwise-14.0.1.0.1.dev7.dist-info/METADATA
odoo14_addon_currency_rate_update_transferwise-14.0.1.0.1.dev7.dist-info/WHEEL
odoo14_addon_currency_rate_update_transferwise-14.0.1.0.1.dev7.dist-info/top_level.txt
odoo14_addon_currency_rate_update_transferwise-14.0.1.0.1.dev7.dist-info/RECORD
